{
  "room_category": {
    "Toilet": {
      "simulation_statistics": [
        {
          "not_completed_agents": 0, 
          "max_evacuation_time": 14.900039, 
          "min_evacuation_time": 14.900039, 
          "exit_flow_rate": 0.06711391829242863, 
          "completed_agents": 1, 
          "max_traveled_distance": 16.315042, 
          "avg_evacuation_time": 14.900039, 
          "avg_traveled_distance": 16.315042, 
          "min_traveled_distance": 16.315042
        }
      ], 
      "bounds": [
        [
          2.28, 
          7.67, 
          5.2, 
          9.86
        ]
      ]
    }, 
    "Bathroom": {
      "simulation_statistics": [
        {
          "not_completed_agents": 0, 
          "max_evacuation_time": 150.004547, 
          "min_evacuation_time": 150.004547, 
          "exit_flow_rate": 0.0, 
          "completed_agents": 0, 
          "max_traveled_distance": 1.637174, 
          "avg_evacuation_time": 150.004547, 
          "avg_traveled_distance": 1.637174, 
          "min_traveled_distance": 1.637174
        }
      ], 
      "bounds": [
        [
          2.28, 
          7.67, 
          5.2, 
          9.86
        ]
      ]
    }, 
    "Room": {
      "simulation_statistics": [
        {
          "not_completed_agents": 0, 
          "max_evacuation_time": 11.550026, 
          "min_evacuation_time": 11.550026, 
          "exit_flow_rate": 0.0865798916816291, 
          "completed_agents": 1, 
          "max_traveled_distance": 10.696157, 
          "avg_evacuation_time": 11.550026, 
          "avg_traveled_distance": 10.696157, 
          "min_traveled_distance": 10.696157
        }, 
        {
          "not_completed_agents": 0, 
          "max_evacuation_time": 13.250032, 
          "min_evacuation_time": 13.250032, 
          "exit_flow_rate": 0.07547151584237684, 
          "completed_agents": 1, 
          "max_traveled_distance": 13.015857, 
          "avg_evacuation_time": 13.250032, 
          "avg_traveled_distance": 13.015857, 
          "min_traveled_distance": 13.015857
        }
      ], 
      "bounds": [
        [
          -0.02, 
          4.58, 
          1.27, 
          9.91
        ], 
        [
          1.19, 
          6.98, 
          3.07, 
          9.86
        ]
      ]
    }, 
    "Living_Room": {
      "simulation_statistics": [
        {
          "not_completed_agents": 0, 
          "max_evacuation_time": 19.949982, 
          "min_evacuation_time": 6.250006, 
          "exit_flow_rate": 0.3007521510545724, 
          "completed_agents": 6, 
          "max_traveled_distance": 19.467154, 
          "avg_evacuation_time": 13.516686666666667, 
          "avg_traveled_distance": 12.846479, 
          "min_traveled_distance": 6.081146
        }
      ], 
      "bounds": [
        [
          5.08, 
          -0.02, 
          10.27, 
          5.54
        ]
      ]
    }, 
    "Bedroom": {
      "simulation_statistics": [
        {
          "not_completed_agents": 0, 
          "max_evacuation_time": 23.549927, 
          "min_evacuation_time": 17.250023, 
          "exit_flow_rate": 0.12738892991048337, 
          "completed_agents": 3, 
          "max_traveled_distance": 18.91284, 
          "avg_evacuation_time": 20.949966666666665, 
          "avg_traveled_distance": 18.26230633333333, 
          "min_traveled_distance": 17.617699
        }, 
        {
          "not_completed_agents": 0, 
          "max_evacuation_time": 20.949966, 
          "min_evacuation_time": 15.700042, 
          "exit_flow_rate": 0.1909310974538097, 
          "completed_agents": 4, 
          "max_traveled_distance": 19.754173, 
          "avg_evacuation_time": 17.812513, 
          "avg_traveled_distance": 18.1605095, 
          "min_traveled_distance": 17.529964
        }
      ], 
      "bounds": [
        [
          1.18, 
          4.57, 
          5.2, 
          7.76
        ], 
        [
          -0.02, 
          9.77, 
          5.2, 
          13.46
        ]
      ]
    }, 
    "Kitchen": {
      "simulation_statistics": [
        {
          "not_completed_agents": 0, 
          "max_evacuation_time": 10.250021, 
          "min_evacuation_time": 3.849998, 
          "exit_flow_rate": 0.487803878645712, 
          "completed_agents": 5, 
          "max_traveled_distance": 7.578765, 
          "avg_evacuation_time": 6.3900066, 
          "avg_traveled_distance": 6.003279, 
          "min_traveled_distance": 5.117622
        }, 
        {
          "not_completed_agents": 0, 
          "max_evacuation_time": 1.35, 
          "min_evacuation_time": 0.0, 
          "exit_flow_rate": 2.222222222222222, 
          "completed_agents": 3, 
          "max_traveled_distance": 1.749372, 
          "avg_evacuation_time": 0.6666666666666666, 
          "avg_traveled_distance": 0.870559, 
          "min_traveled_distance": 0.0
        }
      ], 
      "bounds": [
        [
          -0.02, 
          -0.02, 
          5.17, 
          4.67
        ], 
        [
          -0.02, 
          -0.02, 
          5.17, 
          2.68
        ]
      ]
    }
  }, 
  "room_num": 8, 
  "verts": [
    [
      0.11, 
      0.1
    ], 
    [
      0.1, 
      0.11
    ], 
    [
      0.1, 
      2.07
    ], 
    [
      4.17, 
      2.07
    ], 
    [
      4.18, 
      2.08
    ], 
    [
      4.18, 
      2.17
    ], 
    [
      4.17, 
      2.18
    ], 
    [
      0.1, 
      2.18
    ], 
    [
      0.1, 
      9.76
    ], 
    [
      0.13, 
      9.76
    ], 
    [
      0.14, 
      9.77
    ], 
    [
      0.14, 
      9.87
    ], 
    [
      0.13, 
      9.88
    ], 
    [
      0.1, 
      9.88
    ], 
    [
      0.1, 
      13.35
    ], 
    [
      5.06, 
      13.35
    ], 
    [
      5.06, 
      9.87
    ], 
    [
      4.99, 
      9.87
    ], 
    [
      4.98, 
      9.88
    ], 
    [
      1.0, 
      9.88
    ], 
    [
      0.99, 
      9.87
    ], 
    [
      0.99, 
      9.77
    ], 
    [
      1.0, 
      9.76
    ], 
    [
      2.27, 
      9.76
    ], 
    [
      2.27, 
      8.71
    ], 
    [
      2.28, 
      8.7
    ], 
    [
      2.38, 
      8.7
    ], 
    [
      2.39, 
      8.71
    ], 
    [
      2.39, 
      9.76
    ], 
    [
      5.06, 
      9.76
    ], 
    [
      5.06, 
      7.78
    ], 
    [
      2.39, 
      7.78
    ], 
    [
      2.39, 
      7.84
    ], 
    [
      2.38, 
      7.85
    ], 
    [
      2.28, 
      7.85
    ], 
    [
      2.27, 
      7.84
    ], 
    [
      2.27, 
      7.78
    ], 
    [
      2.16, 
      7.78
    ], 
    [
      2.15, 
      7.77
    ], 
    [
      2.15, 
      7.67
    ], 
    [
      2.16, 
      7.66
    ], 
    [
      5.06, 
      7.66
    ], 
    [
      5.06, 
      4.68
    ], 
    [
      5.02, 
      4.68
    ], 
    [
      5.01, 
      4.67
    ], 
    [
      3.91, 
      4.67
    ], 
    [
      3.9, 
      4.68
    ], 
    [
      1.29, 
      4.68
    ], 
    [
      1.29, 
      7.66
    ], 
    [
      1.3, 
      7.66
    ], 
    [
      1.31, 
      7.67
    ], 
    [
      1.31, 
      7.77
    ], 
    [
      1.3, 
      7.78
    ], 
    [
      1.19, 
      7.78
    ], 
    [
      1.17, 
      7.76
    ], 
    [
      1.17, 
      7.64
    ], 
    [
      1.18, 
      7.63
    ], 
    [
      1.18, 
      4.59
    ], 
    [
      1.17, 
      4.58
    ], 
    [
      1.19, 
      4.56
    ], 
    [
      5.17, 
      4.56
    ], 
    [
      5.18, 
      4.55
    ], 
    [
      6.82, 
      4.55
    ], 
    [
      6.83, 
      4.56
    ], 
    [
      10.16, 
      4.56
    ], 
    [
      10.16, 
      0.1
    ], 
    [
      5.19, 
      0.1
    ], 
    [
      5.19, 
      3.26
    ], 
    [
      5.18, 
      3.27
    ], 
    [
      5.18, 
      3.39
    ], 
    [
      5.17, 
      3.4
    ], 
    [
      5.08, 
      3.4
    ], 
    [
      5.07, 
      3.39
    ], 
    [
      5.07, 
      2.18
    ], 
    [
      5.03, 
      2.18
    ], 
    [
      5.02, 
      2.17
    ], 
    [
      5.02, 
      2.08
    ], 
    [
      5.03, 
      2.07
    ], 
    [
      5.07, 
      2.07
    ], 
    [
      5.07, 
      0.1
    ]
  ], 
  "bbox": {
    "max": [
      10.16, 
      13.35
    ], 
    "min": [
      0.1, 
      0.1
    ]
  }, 
  "id": "b91e3d0bf89a64b6d5594ed462f132f6"
}