[{"position": [52, 118], "square_footage": 13007, "connections": [{"node": 1, "orientation": "east"}, {"node": 2, "orientation": "west"}, {"node": 3, "orientation": "south"}], "label": "Kitchen0"}, {"position": [52, 250], "square_footage": 8890, "connections": [{"node": 0, "orientation": "west"}], "label": "Kitchen0"}, {"position": [139, 175], "square_footage": 15621, "connections": [{"node": 0, "orientation": "east"}, {"node": 3, "orientation": "east"}], "label": "Kitchen0"}, {"position": [145, 269], "square_footage": 22949, "connections": [{"node": 0, "orientation": "north"}, {"node": 2, "orientation": "west"}], "label": "Unknown"}]