[{"position": [176, 52], "square_footage": 7694, "connections": [{"node": 1, "orientation": "south"}, {"node": 4, "orientation": "north"}], "label": "Office0"}, {"position": [259, 52], "square_footage": 8875, "connections": [{"node": 0, "orientation": "north"}], "label": "Office0"}, {"position": [121, 106], "square_footage": 1925, "connections": [{"node": 3, "orientation": "north"}, {"node": 4, "orientation": "west"}], "label": "Toilet0"}, {"position": [52, 52], "square_footage": 6237, "connections": [{"node": 2, "orientation": "south"}, {"node": 4, "orientation": "south"}], "label": "Toilet1"}, {"position": [118, 82], "square_footage": 2744, "connections": [{"node": 0, "orientation": "south"}, {"node": 2, "orientation": "east"}, {"node": 3, "orientation": "north"}], "label": "Toilet1"}]