[{"position": [413, 302], "square_footage": 8956, "connections": [{"node": 1, "orientation": "north"}, {"node": 12, "orientation": "east"}], "label": "Room0"}, {"position": [61, 294], "square_footage": 22927, "connections": [{"node": 0, "orientation": "south"}, {"node": 6, "orientation": "west"}, {"node": 7, "orientation": "east"}], "label": "Room1"}, {"position": [260, 142], "square_footage": 21644, "connections": [{"node": 6, "orientation": "north"}, {"node": 8, "orientation": "west"}], "label": "Room2"}, {"position": [278, 366], "square_footage": 16899, "connections": [{"node": 7, "orientation": "north"}, {"node": 11, "orientation": "east"}], "label": "Room3"}, {"position": [61, 141], "square_footage": 19036, "connections": [{"node": 6, "orientation": "south"}, {"node": 9, "orientation": "west"}], "label": "Room4"}, {"position": [61, 366], "square_footage": 21374, "connections": [{"node": 7, "orientation": "south"}, {"node": 10, "orientation": "east"}], "label": "Room5"}, {"position": [191, 141], "square_footage": 8928, "connections": [{"node": 1, "orientation": "east"}, {"node": 2, "orientation": "south"}, {"node": 4, "orientation": "north"}], "label": "Room4"}, {"position": [208, 483], "square_footage": 8653, "connections": [{"node": 1, "orientation": "west"}, {"node": 3, "orientation": "south"}, {"node": 5, "orientation": "north"}, {"node": 11, "orientation": "east"}], "label": "Room5"}, {"position": [263, 52], "square_footage": 12152, "connections": [{"node": 2, "orientation": "east"}], "label": "Room8"}, {"position": [52, 52], "square_footage": 12591, "connections": [{"node": 4, "orientation": "east"}], "label": "Room9"}, {"position": [52, 591], "square_footage": 12692, "connections": [{"node": 5, "orientation": "west"}], "label": "Room10"}, {"position": [257, 495], "square_footage": 14871, "connections": [{"node": 3, "orientation": "west"}, {"node": 7, "orientation": "west"}], "label": "Room3"}, {"position": [415, 404], "square_footage": 5159, "connections": [{"node": 0, "orientation": "west"}], "label": "Unknown"}]