[{"position": [52, 131], "square_footage": 24209, "connections": [{"node": 1, "orientation": "south"}, {"node": 3, "orientation": "south"}], "label": "Guest_Room0"}, {"position": [162, 169], "square_footage": 23275, "connections": [{"node": 0, "orientation": "north"}, {"node": 2, "orientation": "west"}, {"node": 3, "orientation": "east"}], "label": "Guest_Room0"}, {"position": [242, 52], "square_footage": 5393, "connections": [{"node": 1, "orientation": "east"}], "label": "Toilet0"}, {"position": [166, 281], "square_footage": 31787, "connections": [{"node": 0, "orientation": "north"}, {"node": 1, "orientation": "west"}], "label": "Unknown"}]