[{"position": [384, 55], "square_footage": 21154, "connections": [{"node": 4, "orientation": "north"}], "label": "Toilet0"}, {"position": [178, 187], "square_footage": 41405, "connections": [{"node": 3, "orientation": "south"}, {"node": 4, "orientation": "west"}, {"node": 7, "orientation": "east"}], "label": "Living_Room0"}, {"position": [332, 444], "square_footage": 11520, "connections": [{"node": 3, "orientation": "west"}], "label": "Gym0"}, {"position": [326, 389], "square_footage": 28435, "connections": [{"node": 1, "orientation": "north"}, {"node": 2, "orientation": "east"}], "label": "Living_Room0"}, {"position": [120, 55], "square_footage": 32899, "connections": [{"node": 0, "orientation": "south"}, {"node": 1, "orientation": "east"}], "label": "Bedroom0"}, {"position": [176, 617], "square_footage": 47032, "connections": [{"node": 6, "orientation": "north"}, {"node": 7, "orientation": "west"}], "label": "Dining_Room0"}, {"position": [52, 615], "square_footage": 25687, "connections": [{"node": 5, "orientation": "south"}], "label": "Garage0"}, {"position": [178, 444], "square_footage": 24188, "connections": [{"node": 1, "orientation": "west"}, {"node": 5, "orientation": "east"}], "label": "Unknown"}]